{
  "generatedAt": "2026-07-12T02:33:20.832Z",
  "summary": {
    "schools": 323,
    "programs": 1099,
    "sources": 21990,
    "contacts": 346,
    "programDeadlines": 1099,
    "auditFlags": 2661,
    "openFlags": 1099,
    "verificationRate": 100,
    "duplicateSchoolsRemaining": 0,
    "missingTuitionCount": 0,
    "missingSourcesCount": 0,
    "incompleteMetadataCount": 2
  },
  "issues": {
    "missingTuition": [],
    "incorrectTuition": [],
    "duplicateSchools": [],
    "inconsistentCurrencies": [],
    "outdatedDeadlines": [],
    "brokenApplicationLinks": [],
    "invalidEmails": [],
    "missingContacts": [
      {
        "schoolId": 120,
        "name": "Université Paris 8 Vincennes-Saint-Denis"
      },
      {
        "schoolId": 145,
        "name": "The Open University (UK)"
      },
      {
        "schoolId": 244,
        "name": "University of Dundee"
      },
      {
        "schoolId": 330,
        "name": "University of Bergen (UiB)"
      }
    ],
    "incompleteMetadata": [
      {
        "programId": 31,
        "name": "MSc in Risk & Finance",
        "missing": [
          "studyMode",
          "degreeAwarded",
          "programmeUrl"
        ]
      },
      {
        "programId": 626,
        "name": "Master Finance Quantitative / Ingénierie Financière",
        "missing": [
          "studyMode",
          "degreeAwarded",
          "programmeUrl"
        ]
      }
    ],
    "missingSources": [],
    "orphanedRecords": []
  },
  "completeness": {
    "tuitionYearly": {
      "filled": 1099,
      "total": 1099,
      "pct": 100
    },
    "applicationUrl": {
      "filled": 1099,
      "total": 1099,
      "pct": 100
    },
    "programmeUrl": {
      "filled": 1097,
      "total": 1099,
      "pct": 100
    },
    "sourceUrl": {
      "filled": 1099,
      "total": 1099,
      "pct": 100
    },
    "ieltsMinScore": {
      "filled": 1099,
      "total": 1099,
      "pct": 100
    },
    "admissionsEmail": {
      "filled": 1087,
      "total": 1099,
      "pct": 99
    },
    "faculty": {
      "filled": 454,
      "total": 1099,
      "pct": 41
    },
    "studyMode": {
      "filled": 1097,
      "total": 1099,
      "pct": 100
    },
    "internationalTuition": {
      "filled": 1069,
      "total": 1099,
      "pct": 97
    },
    "degreeAwarded": {
      "filled": 454,
      "total": 1099,
      "pct": 41
    },
    "gmatRequired": {
      "filled": 1099,
      "total": 1099,
      "pct": 100
    }
  },
  "verification": {
    "verified": 1097,
    "pending": 2,
    "manual": 0,
    "total": 1099
  }
}
